{
  "lookup": {
    "rules": {
      "[{\"prev_action\": {\"action_name\": \"action_listen\"}, \"user\": {\"intent\": \"CrossValidation\"}}]": "utter_CrossValidation",
      "[{\"prev_action\": {\"action_name\": \"action_listen\"}, \"user\": {\"intent\": \"CrossValidation\"}}, {\"prev_action\": {\"action_name\": \"utter_CrossValidation\"}, \"user\": {\"intent\": \"CrossValidation\"}}]": "action_listen",
      "[{\"prev_action\": {\"action_name\": \"action_listen\"}, \"user\": {\"intent\": \"SupervisedLearning\"}}]": "utter_SupervisedLearning",
      "[{\"prev_action\": {\"action_name\": \"action_listen\"}, \"user\": {\"intent\": \"SupervisedLearning\"}}, {\"prev_action\": {\"action_name\": \"utter_SupervisedLearning\"}, \"user\": {\"intent\": \"SupervisedLearning\"}}]": "action_listen",
      "[{\"prev_action\": {\"action_name\": \"action_listen\"}, \"user\": {\"intent\": \"OverfittingUnderfitting\"}}]": "utter_OverfittingUnderfitting",
      "[{\"prev_action\": {\"action_name\": \"action_listen\"}, \"user\": {\"intent\": \"OverfittingUnderfitting\"}}, {\"prev_action\": {\"action_name\": \"utter_OverfittingUnderfitting\"}, \"user\": {\"intent\": \"OverfittingUnderfitting\"}}]": "action_listen",
      "[{\"prev_action\": {\"action_name\": \"action_listen\"}, \"user\": {\"intent\": \"EnsembleLearning\"}}]": "utter_EnsembleLearning",
      "[{\"prev_action\": {\"action_name\": \"action_listen\"}, \"user\": {\"intent\": \"EnsembleLearning\"}}, {\"prev_action\": {\"action_name\": \"utter_EnsembleLearning\"}, \"user\": {\"intent\": \"EnsembleLearning\"}}]": "action_listen",
      "[{\"prev_action\": {\"action_name\": \"action_listen\"}, \"user\": {\"intent\": \"NeuralNetworks\"}}]": "utter_NeuralNetworks",
      "[{\"prev_action\": {\"action_name\": \"action_listen\"}, \"user\": {\"intent\": \"NeuralNetworks\"}}, {\"prev_action\": {\"action_name\": \"utter_NeuralNetworks\"}, \"user\": {\"intent\": \"NeuralNetworks\"}}]": "action_listen",
      "[{\"prev_action\": {\"action_name\": \"action_listen\"}, \"user\": {\"intent\": \"goodbye\"}}]": "utter_goodbye",
      "[{\"prev_action\": {\"action_name\": \"action_listen\"}, \"user\": {\"intent\": \"goodbye\"}}, {\"prev_action\": {\"action_name\": \"utter_goodbye\"}, \"user\": {\"intent\": \"goodbye\"}}]": "action_listen",
      "[{\"prev_action\": {\"action_name\": \"action_listen\"}, \"user\": {\"intent\": \"TimeSeriesAnalysis\"}}]": "utter_TimeSeriesAnalysis",
      "[{\"prev_action\": {\"action_name\": \"action_listen\"}, \"user\": {\"intent\": \"TimeSeriesAnalysis\"}}, {\"prev_action\": {\"action_name\": \"utter_TimeSeriesAnalysis\"}, \"user\": {\"intent\": \"TimeSeriesAnalysis\"}}]": "action_listen",
      "[{\"prev_action\": {\"action_name\": \"action_listen\"}, \"user\": {\"intent\": \"HyperparameterTuning\"}}]": "utter_HyperparameterTuning",
      "[{\"prev_action\": {\"action_name\": \"action_listen\"}, \"user\": {\"intent\": \"HyperparameterTuning\"}}, {\"prev_action\": {\"action_name\": \"utter_HyperparameterTuning\"}, \"user\": {\"intent\": \"HyperparameterTuning\"}}]": "action_listen",
      "[{\"prev_action\": {\"action_name\": \"action_listen\"}, \"user\": {\"intent\": \"ReinforcementLearning\"}}]": "utter_ReinforcementLearning",
      "[{\"prev_action\": {\"action_name\": \"action_listen\"}, \"user\": {\"intent\": \"ReinforcementLearning\"}}, {\"prev_action\": {\"action_name\": \"utter_ReinforcementLearning\"}, \"user\": {\"intent\": \"ReinforcementLearning\"}}]": "action_listen",
      "[{\"prev_action\": {\"action_name\": \"action_listen\"}, \"user\": {\"intent\": \"FeatureEngineering\"}}]": "utter_FeatureEngineering",
      "[{\"prev_action\": {\"action_name\": \"action_listen\"}, \"user\": {\"intent\": \"FeatureEngineering\"}}, {\"prev_action\": {\"action_name\": \"utter_FeatureEngineering\"}, \"user\": {\"intent\": \"FeatureEngineering\"}}]": "action_listen",
      "[{\"prev_action\": {\"action_name\": \"action_listen\"}, \"user\": {\"intent\": \"TransferLearning\"}}]": "utter_TransferLearning",
      "[{\"prev_action\": {\"action_name\": \"action_listen\"}, \"user\": {\"intent\": \"TransferLearning\"}}, {\"prev_action\": {\"action_name\": \"utter_TransferLearning\"}, \"user\": {\"intent\": \"TransferLearning\"}}]": "action_listen",
      "[{\"prev_action\": {\"action_name\": \"action_listen\"}, \"user\": {\"intent\": \"BiasFairnessMachineLearning\"}}]": "utter_BiasFairnessMachineLearning",
      "[{\"prev_action\": {\"action_name\": \"action_listen\"}, \"user\": {\"intent\": \"BiasFairnessMachineLearning\"}}, {\"prev_action\": {\"action_name\": \"utter_BiasFairnessMachineLearning\"}, \"user\": {\"intent\": \"BiasFairnessMachineLearning\"}}]": "action_listen",
      "[{\"prev_action\": {\"action_name\": \"action_listen\"}, \"user\": {\"intent\": \"UnsupervisedLearning\"}}]": "utter_UnsupervisedLearning",
      "[{\"prev_action\": {\"action_name\": \"action_listen\"}, \"user\": {\"intent\": \"UnsupervisedLearning\"}}, {\"prev_action\": {\"action_name\": \"utter_UnsupervisedLearning\"}, \"user\": {\"intent\": \"UnsupervisedLearning\"}}]": "action_listen",
      "[{\"prev_action\": {\"action_name\": \"action_listen\"}, \"user\": {\"intent\": \"GradientDescent\"}}]": "utter_GradientDescent",
      "[{\"prev_action\": {\"action_name\": \"action_listen\"}, \"user\": {\"intent\": \"GradientDescent\"}}, {\"prev_action\": {\"action_name\": \"utter_GradientDescent\"}, \"user\": {\"intent\": \"GradientDescent\"}}]": "action_listen",
      "[{\"prev_action\": {\"action_name\": \"action_listen\"}, \"user\": {\"intent\": \"ComputerVision\"}}]": "utter_ComputerVision",
      "[{\"prev_action\": {\"action_name\": \"action_listen\"}, \"user\": {\"intent\": \"ComputerVision\"}}, {\"prev_action\": {\"action_name\": \"utter_ComputerVision\"}, \"user\": {\"intent\": \"ComputerVision\"}}]": "action_listen",
      "[{\"prev_action\": {\"action_name\": \"action_listen\"}, \"user\": {\"intent\": \"bot_challenge\"}}]": "utter_iamabot",
      "[{\"prev_action\": {\"action_name\": \"action_listen\"}, \"user\": {\"intent\": \"bot_challenge\"}}, {\"prev_action\": {\"action_name\": \"utter_iamabot\"}, \"user\": {\"intent\": \"bot_challenge\"}}]": "action_listen",
      "[{\"prev_action\": {\"action_name\": \"action_listen\"}, \"user\": {\"intent\": \"NaturalLanguageProcessing\"}}]": "utter_NaturalLanguageProcessing",
      "[{\"prev_action\": {\"action_name\": \"action_listen\"}, \"user\": {\"intent\": \"NaturalLanguageProcessing\"}}, {\"prev_action\": {\"action_name\": \"utter_NaturalLanguageProcessing\"}, \"user\": {\"intent\": \"NaturalLanguageProcessing\"}}]": "action_listen"
    },
    "rule_only_slots": [],
    "rule_only_loops": [],
    "rules_for_loop_unhappy_path": {},
    "rules_not_in_stories": [
      "[{\"prev_action\": {\"action_name\": \"action_listen\"}, \"user\": {\"intent\": \"HyperparameterTuning\"}}]",
      "[{\"prev_action\": {\"action_name\": \"action_listen\"}, \"user\": {\"intent\": \"CrossValidation\"}}, {\"prev_action\": {\"action_name\": \"utter_CrossValidation\"}, \"user\": {\"intent\": \"CrossValidation\"}}]",
      "[{\"prev_action\": {\"action_name\": \"action_listen\"}, \"user\": {\"intent\": \"goodbye\"}}, {\"prev_action\": {\"action_name\": \"utter_goodbye\"}, \"user\": {\"intent\": \"goodbye\"}}]",
      "[{\"prev_action\": {\"action_name\": \"action_listen\"}, \"user\": {\"intent\": \"TransferLearning\"}}]",
      "[{\"prev_action\": {\"action_name\": \"action_listen\"}, \"user\": {\"intent\": \"OverfittingUnderfitting\"}}, {\"prev_action\": {\"action_name\": \"utter_OverfittingUnderfitting\"}, \"user\": {\"intent\": \"OverfittingUnderfitting\"}}]",
      "predicting default action with intent session_start",
      "[{\"prev_action\": {\"action_name\": \"action_listen\"}, \"user\": {\"intent\": \"HyperparameterTuning\"}}, {\"prev_action\": {\"action_name\": \"utter_HyperparameterTuning\"}, \"user\": {\"intent\": \"HyperparameterTuning\"}}]",
      "[{\"prev_action\": {\"action_name\": \"action_listen\"}, \"user\": {\"intent\": \"SupervisedLearning\"}}]",
      "[{\"prev_action\": {\"action_name\": \"action_listen\"}, \"user\": {\"intent\": \"TimeSeriesAnalysis\"}}]",
      "[{\"prev_action\": {\"action_name\": \"action_listen\"}, \"user\": {\"intent\": \"ComputerVision\"}}, {\"prev_action\": {\"action_name\": \"utter_ComputerVision\"}, \"user\": {\"intent\": \"ComputerVision\"}}]",
      "[{\"prev_action\": {\"action_name\": \"action_listen\"}, \"user\": {\"intent\": \"CrossValidation\"}}]",
      "[{\"prev_action\": {\"action_name\": \"action_listen\"}, \"user\": {\"intent\": \"NaturalLanguageProcessing\"}}]",
      "[{\"prev_action\": {\"action_name\": \"action_listen\"}, \"user\": {\"intent\": \"GradientDescent\"}}, {\"prev_action\": {\"action_name\": \"utter_GradientDescent\"}, \"user\": {\"intent\": \"GradientDescent\"}}]",
      "[{\"prev_action\": {\"action_name\": \"action_listen\"}, \"user\": {\"intent\": \"FeatureEngineering\"}}]",
      "[{\"prev_action\": {\"action_name\": \"action_listen\"}, \"user\": {\"intent\": \"EnsembleLearning\"}}, {\"prev_action\": {\"action_name\": \"utter_EnsembleLearning\"}, \"user\": {\"intent\": \"EnsembleLearning\"}}]",
      "[{\"prev_action\": {\"action_name\": \"action_listen\"}, \"user\": {\"intent\": \"goodbye\"}}]",
      "[{\"prev_action\": {\"action_name\": \"action_listen\"}, \"user\": {\"intent\": \"UnsupervisedLearning\"}}, {\"prev_action\": {\"action_name\": \"utter_UnsupervisedLearning\"}, \"user\": {\"intent\": \"UnsupervisedLearning\"}}]",
      "[{\"prev_action\": {\"action_name\": \"action_listen\"}, \"user\": {\"intent\": \"ReinforcementLearning\"}}, {\"prev_action\": {\"action_name\": \"utter_ReinforcementLearning\"}, \"user\": {\"intent\": \"ReinforcementLearning\"}}]",
      "[{\"prev_action\": {\"action_name\": \"action_listen\"}, \"user\": {\"intent\": \"EnsembleLearning\"}}]",
      "[{\"prev_action\": {\"action_name\": \"action_listen\"}, \"user\": {\"intent\": \"GradientDescent\"}}]",
      "predicting default action with intent restart",
      "[{\"prev_action\": {\"action_name\": \"action_listen\"}, \"user\": {\"intent\": \"bot_challenge\"}}, {\"prev_action\": {\"action_name\": \"utter_iamabot\"}, \"user\": {\"intent\": \"bot_challenge\"}}]",
      "[{\"prev_action\": {\"action_name\": \"action_listen\"}, \"user\": {\"intent\": \"OverfittingUnderfitting\"}}]",
      "[{\"prev_action\": {\"action_name\": \"action_listen\"}, \"user\": {\"intent\": \"NeuralNetworks\"}}]",
      "[{\"prev_action\": {\"action_name\": \"action_listen\"}, \"user\": {\"intent\": \"NeuralNetworks\"}}, {\"prev_action\": {\"action_name\": \"utter_NeuralNetworks\"}, \"user\": {\"intent\": \"NeuralNetworks\"}}]",
      "[{\"prev_action\": {\"action_name\": \"action_listen\"}, \"user\": {\"intent\": \"FeatureEngineering\"}}, {\"prev_action\": {\"action_name\": \"utter_FeatureEngineering\"}, \"user\": {\"intent\": \"FeatureEngineering\"}}]",
      "[{\"prev_action\": {\"action_name\": \"action_listen\"}, \"user\": {\"intent\": \"SupervisedLearning\"}}, {\"prev_action\": {\"action_name\": \"utter_SupervisedLearning\"}, \"user\": {\"intent\": \"SupervisedLearning\"}}]",
      "predicting default action with intent back",
      "[{\"prev_action\": {\"action_name\": \"action_listen\"}, \"user\": {\"intent\": \"UnsupervisedLearning\"}}]",
      "[{\"prev_action\": {\"action_name\": \"action_listen\"}, \"user\": {\"intent\": \"bot_challenge\"}}]",
      "[{\"prev_action\": {\"action_name\": \"action_listen\"}, \"user\": {\"intent\": \"ReinforcementLearning\"}}]",
      "[{\"prev_action\": {\"action_name\": \"action_listen\"}, \"user\": {\"intent\": \"NaturalLanguageProcessing\"}}, {\"prev_action\": {\"action_name\": \"utter_NaturalLanguageProcessing\"}, \"user\": {\"intent\": \"NaturalLanguageProcessing\"}}]",
      "[{\"prev_action\": {\"action_name\": \"action_listen\"}, \"user\": {\"intent\": \"BiasFairnessMachineLearning\"}}]",
      "[{\"prev_action\": {\"action_name\": \"action_listen\"}, \"user\": {\"intent\": \"BiasFairnessMachineLearning\"}}, {\"prev_action\": {\"action_name\": \"utter_BiasFairnessMachineLearning\"}, \"user\": {\"intent\": \"BiasFairnessMachineLearning\"}}]",
      "[{\"prev_action\": {\"action_name\": \"action_listen\"}, \"user\": {\"intent\": \"TransferLearning\"}}, {\"prev_action\": {\"action_name\": \"utter_TransferLearning\"}, \"user\": {\"intent\": \"TransferLearning\"}}]",
      "[{\"prev_action\": {\"action_name\": \"action_listen\"}, \"user\": {\"intent\": \"TimeSeriesAnalysis\"}}, {\"prev_action\": {\"action_name\": \"utter_TimeSeriesAnalysis\"}, \"user\": {\"intent\": \"TimeSeriesAnalysis\"}}]",
      "[{\"prev_action\": {\"action_name\": \"action_listen\"}, \"user\": {\"intent\": \"ComputerVision\"}}]"
    ]
  }
}